wordlerer/__init__.py
wordlerer/browser.py
wordlerer/cli.py
wordlerer/english_words.py
wordlerer/models.py
wordlerer/utils.py
wordlerer/wordlerer.py
wordlerer-0.1.1.dist-info/LICENSE
wordlerer-0.1.1.dist-info/WHEEL
wordlerer-0.1.1.dist-info/METADATA
wordlerer-0.1.1.dist-info/RECORD
